Metadata-Version: 2.1
Name: cagou
Version: 0.7.0
Summary: Desktop/Android frontend for Salut à Toi XMPP client
Home-page: https://salut-a-toi.org
Author: Association « Salut à Toi »
Author-email: contact@goffi.org
License: UNKNOWN
Platform: UNKNOWN
Classifier: Development Status :: 3 - Alpha
Classifier: Programming Language :: Python :: 2.7
Classifier: Programming Language :: Python :: 2 :: Only
Classifier: Environment :: X11 Applications
Classifier: Framework :: Twisted
Classifier: License :: OSI Approved :: GNU Affero General Public License v3 or later (AGPLv3+)
Classifier: Operating System :: POSIX :: Linux
Classifier: Operating System :: Android
Classifier: Topic :: Internet :: XMPP
Classifier: Topic :: Communications :: Chat
Classifier: Intended Audience :: End Users/Desktop
Requires-Python: ~=2.7
Requires-Dist: kivy (>=1.10.0)
Requires-Dist: pillow
Requires-Dist: plyer
Requires-Dist: sat (>=0.7.0dev0)
